jupyterlab_white_theme/.DS_Store
jupyterlab_white_theme/__init__.py
jupyterlab_white_theme/_version.py
jupyterlab_white_theme/labextension/.DS_Store
jupyterlab_white_theme/labextension/package.json
jupyterlab_white_theme/labextension/static/568.5191f01b35b29df8352d.js
jupyterlab_white_theme/labextension/static/568.aded9c36181c29a7c1b3.js
jupyterlab_white_theme/labextension/static/remoteEntry.8bcb2556355d4f1f5f3d.js
jupyterlab_white_theme/labextension/static/remoteEntry.cce1fab5e96bf9502042.js
jupyterlab_white_theme/labextension/static/style.js
jupyterlab_white_theme/labextension/static/third-party-licenses.json
jupyterlab_white_theme/labextension/themes/@alalalalaki/jupyter-white-theme/index.css
jupyterlab_white_theme/labextension/themes/@alalalalaki/jupyter-white-theme/index.js
jupyterlab_white_theme-0.1.1.data/data/share/jupyter/labextensions/@alalalalaki/jupyter-white-theme/install.json
jupyterlab_white_theme-0.1.1.data/data/share/jupyter/labextensions/@alalalalaki/jupyter-white-theme/package.json
jupyterlab_white_theme-0.1.1.data/data/share/jupyter/labextensions/@alalalalaki/jupyter-white-theme/static/568.5191f01b35b29df8352d.js
jupyterlab_white_theme-0.1.1.data/data/share/jupyter/labextensions/@alalalalaki/jupyter-white-theme/static/remoteEntry.cce1fab5e96bf9502042.js
jupyterlab_white_theme-0.1.1.data/data/share/jupyter/labextensions/@alalalalaki/jupyter-white-theme/static/style.js
jupyterlab_white_theme-0.1.1.data/data/share/jupyter/labextensions/@alalalalaki/jupyter-white-theme/static/third-party-licenses.json
jupyterlab_white_theme-0.1.1.data/data/share/jupyter/labextensions/@alalalalaki/jupyter-white-theme/themes/@alalalalaki/jupyter-white-theme/index.css
jupyterlab_white_theme-0.1.1.data/data/share/jupyter/labextensions/@alalalalaki/jupyter-white-theme/themes/@alalalalaki/jupyter-white-theme/index.js
jupyterlab_white_theme-0.1.1.dist-info/LICENSE
jupyterlab_white_theme-0.1.1.dist-info/METADATA
jupyterlab_white_theme-0.1.1.dist-info/WHEEL
jupyterlab_white_theme-0.1.1.dist-info/top_level.txt
jupyterlab_white_theme-0.1.1.dist-info/RECORD
